{
  "blocked_net": "BEMF_C_CH1",
  "blocked_net_priority": 70,
  "board_sha": "e70587444ad4f1539efa5b9361b2a12c67891ca9",
  "cascade_depth": 1,
  "committed": true,
  "conflict_set": [
    "CSA_C_OUT_CH1"
  ],
  "conflict_set_priorities": [
    40
  ],
  "deviation_log_ref": "",
  "phase_symmetric_mirror_status": "N/A",
  "phase_symmetric_peers": [],
  "rerouted": {
    "CSA_C_OUT_CH1": {
      "depth": 1,
      "length_mm": 176.35,
      "path": "26 segs",
      "summary": "ROUTED"
    }
  },
  "rollback_reason": "",
  "schema_version": 1,
  "shorts_post": 10,
  "shorts_pre": 10,
  "subsystem": "CH1",
  "timestamp_iso": "2026-05-28T15:51:14.720471Z"
}